phoenix/client/__init__.py
phoenix/client/client.py
phoenix/client/constants.py
phoenix/client/py.typed
phoenix/client/__generated__/__init__.py
phoenix/client/__generated__/v1/.gitignore
phoenix/client/__generated__/v1/__init__.py
phoenix/client/exceptions/__init__.py
phoenix/client/experiments/__init__.py
phoenix/client/helpers/__init__.py
phoenix/client/helpers/sdk/__init__.py
phoenix/client/helpers/sdk/anthropic/__init__.py
phoenix/client/helpers/sdk/anthropic/messages.py
phoenix/client/helpers/sdk/google_generativeai/__init__.py
phoenix/client/helpers/sdk/google_generativeai/generate_content.py
phoenix/client/helpers/sdk/openai/__init__.py
phoenix/client/helpers/sdk/openai/chat.py
phoenix/client/helpers/spans/__init__.py
phoenix/client/helpers/spans/rag.py
phoenix/client/resources/__init__.py
phoenix/client/resources/annotations/__init__.py
phoenix/client/resources/datasets/__init__.py
phoenix/client/resources/experiments/__init__.py
phoenix/client/resources/experiments/evaluators.py
phoenix/client/resources/experiments/types.py
phoenix/client/resources/projects/__init__.py
phoenix/client/resources/prompts/__init__.py
phoenix/client/resources/sessions/__init__.py
phoenix/client/resources/spans/__init__.py
phoenix/client/resources/traces/__init__.py
phoenix/client/types/__init__.py
phoenix/client/types/prompts.py
phoenix/client/types/spans.py
phoenix/client/utils/__init__.py
phoenix/client/utils/annotation_helpers.py
phoenix/client/utils/config.py
phoenix/client/utils/encode_path_param.py
phoenix/client/utils/executors.py
phoenix/client/utils/id_handling.py
phoenix/client/utils/parse_env_headers.py
phoenix/client/utils/rate_limiters.py
phoenix/client/utils/template_formatters.py
arize_phoenix_client-1.28.0.dist-info/METADATA
arize_phoenix_client-1.28.0.dist-info/WHEEL
arize_phoenix_client-1.28.0.dist-info/licenses/IP_NOTICE
arize_phoenix_client-1.28.0.dist-info/licenses/LICENSE
arize_phoenix_client-1.28.0.dist-info/RECORD
