Metadata-Version: 2.4
Name: arize-phoenix-client
Version: 1.28.0
Summary: LLM Observability
Project-URL: Documentation, https://arize.com/docs/phoenix/
Project-URL: Issues, https://github.com/Arize-ai/phoenix/issues
Project-URL: Source, https://github.com/Arize-ai/phoenix
Author-email: Arize AI <phoenix-devs@arize.com>
License: Apache-2.0
License-File: IP_NOTICE
License-File: LICENSE
Keywords: Explainability,Monitoring,Observability
Classifier: Programming Language :: Python
Classifier: Programming Language :: Python :: 3.9
Classifier: Programming Language :: Python :: 3.10
Classifier: Programming Language :: Python :: 3.11
Classifier: Programming Language :: Python :: 3.12
Classifier: Programming Language :: Python :: 3.13
Requires-Python: <3.14,>=3.9
Requires-Dist: httpx
Requires-Dist: openinference-instrumentation>=0.1.20
Requires-Dist: openinference-semantic-conventions
Requires-Dist: opentelemetry-exporter-otlp
Requires-Dist: opentelemetry-sdk
Requires-Dist: tqdm
Requires-Dist: typing-extensions
